topsis/__init__.py
topsis/__main__.py
Topsis_Vansh_102218059-1.0.dist-info/LICENSE
Topsis_Vansh_102218059-1.0.dist-info/METADATA
Topsis_Vansh_102218059-1.0.dist-info/WHEEL
Topsis_Vansh_102218059-1.0.dist-info/entry_points.txt
Topsis_Vansh_102218059-1.0.dist-info/top_level.txt
Topsis_Vansh_102218059-1.0.dist-info/RECORD
